README.rst
setup.py
Discharge.egg-info/PKG-INFO
Discharge.egg-info/SOURCES.txt
Discharge.egg-info/dependency_links.txt
Discharge.egg-info/requires.txt
Discharge.egg-info/top_level.txt
discharge/__init__.py
discharge/buildcontext.py
discharge/cmd.py
discharge/exceptions.py
discharge/server.py
discharge/site.py
discharge/plugins/__init__.py
discharge/plugins/jinja2_templates.py
discharge/plugins/markdown.py
discharge/plugins/plugin.py
discharge/plugins/robots.py
discharge/plugins/jinja2_filters/__init__.py
discharge/plugins/jinja2_filters/highlight.py
scripts/discharge