Metadata-Version: 1.0
Name: Discharge
Version: 0.2.1
Summary: A static site generator
Home-page: https://github.com/RichardOfWard/discharge
Author: Richard Ward
Author-email: richard@richard.ward.name
License: UNKNOWN
Platform: UNKNOWN
